<?xml version="1.0" encoding="UTF-8"?>
<analysisEngineDescription xmlns="http://uima.apache.org/resourceSpecifier">
  <frameworkImplementation>org.apache.uima.java</frameworkImplementation>
  <primitive>true</primitive>  <annotatorImplementationName>edu.cmu.deiis.annotator.TestElementAnnotator</annotatorImplementationName>
  <analysisEngineMetaData>
    <name>TestElementAnnotator</name>
    <description>This annotator class splits a given document into question and answer
It will also assign assign  sentiment to each sentence</description>
    <version>1.0</version>
    <vendor/>
    <configurationParameters>
      <configurationParameter>
        <name>casFilePath</name>
        <type>String</type>
        <multiValued>false</multiValued>
        <mandatory>false</mandatory>
      </configurationParameter>
    </configurationParameters>
    <configurationParameterSettings/>
    <typeSystemDescription>
      <imports>
        <import location="/home/richie/git/hw2-skohli/hw2-skohli/src/main/resources/descriptors/deiis_types.xml"/>
      </imports>
      <types>
        <typeDescription>
          <name>com.cmu.csd.types.TestElementAnnotation</name>
          <description/>
          <supertypeName>uima.tcas.Annotation</supertypeName>
        </typeDescription>
      </types>
    </typeSystemDescription>
    <typePriorities/>
    <fsIndexCollection/>
    <capabilities>
      <capability>
        <inputs/>
        <outputs/>
        <languagesSupported/>
      </capability>
    </capabilities>
  <operationalProperties>
      <modifiesCas>true</modifiesCas>
      <multipleDeploymentAllowed>true</multipleDeploymentAllowed>
      <outputsNewCASes>false</outputsNewCASes>
    </operationalProperties>
  </analysisEngineMetaData>
  <resourceManagerConfiguration/>
</analysisEngineDescription>
